<?xml version="1.0" encoding="UTF-8"?>
<students>
    <student>
        <id>1</id>
        <name>Rohan Kumar Patel</name>
        <age>22</age>
        <grade>A</grade>
    </student>
    <student>
        <id>2</id>
        <name>B Ezra William</name>
        <age>25</age>
        <grade>A</grade>
    </student>
    <student>
        <id>3</id>
        <name>Roshan Rajan Chand</name>
        <age>23</age>
        <grade>A+</grade>
    </student>
    <student>
        <id>4</id>
        <name>Vishal Kumar Bhunjia</name>
        <age>25</age>
        <grade>A+</grade>
    </student>
    <student>
        <id>5</id>
        <name>Rajat Khamari</name>
        <age>22</age>
        <grade>A</grade>
    </student>
    <student>
        <id>6</id>
        <name>Debadatta Mahanta</name>
        <age>22</age>
        <grade>A</grade>
    </student>
    <student>
        <id>7</id>
        <name>Chuleswar Rana</name>
        <age>22</age>
        <grade>A+</grade>
    </student>
    <student>
        <id>8</id>
        <name>Lotus Kumar Sahu</name>
        <age>22</age>
        <grade>A</grade>
    </student>
    <student>
        <id>9</id>
        <name>Roshan Patel</name>
        <age>23</age>
        <grade>A</grade>
    </student>
    <student>
        <id>10</id>
        <name>Abhisek Tripathy</name>
        <age>23</age>
        <grade>A+</grade>
    </student>
</students>
